typed_classproperties/__init__.py
typed_classproperties/py.typed
typed_classproperties-1.4.3.dist-info/METADATA
typed_classproperties-1.4.3.dist-info/WHEEL
typed_classproperties-1.4.3.dist-info/licenses/LICENSE
typed_classproperties-1.4.3.dist-info/RECORD
