Metadata-Version: 2.4
Name: typed_classproperties
Version: 1.4.3
Summary: Typed decorators for classproperty and cached_classproperty.
Project-URL: Issues, https://github.com/CarrotManMatt/typed_classproperties/issues
Project-URL: Releases, https://github.com/CarrotManMatt/typed_classproperties/releases
Project-URL: Repository, https://github.com/CarrotManMatt/typed_classproperties
Author-email: Jonathan Clarke <jonathan.a.clarke@gmail.com>, Matt Norton <matt@carrotmanmatt.com>
Maintainer-email: Matt Norton <matt@carrotmanmatt.com>
License-Expression: MIT
License-File: LICENSE
Keywords: classmethod,decorator,property
Classifier: Development Status :: 5 - Production/Stable
Classifier: Intended Audience :: Developers
Classifier: Operating System :: OS Independent
Classifier: Programming Language :: Python :: 3 :: Only
Classifier: Programming Language :: Python :: 3.10
Classifier: Programming Language :: Python :: 3.11
Classifier: Programming Language :: Python :: 3.12
Classifier: Programming Language :: Python :: 3.13
Classifier: Programming Language :: Python :: 3.14
Classifier: Programming Language :: Python :: 3.15
Classifier: Topic :: Software Development
Classifier: Topic :: Utilities
Classifier: Typing :: Typed
Requires-Python: >=3.10
Requires-Dist: typing-extensions; python_version < '3.12'
